libretrofuzz/__init__.py
libretrofuzz/__main__.py
libretrofuzz-3.7.0.dist-info/entry_points.txt
libretrofuzz-3.7.0.dist-info/LICENSE
libretrofuzz-3.7.0.dist-info/WHEEL
libretrofuzz-3.7.0.dist-info/METADATA
libretrofuzz-3.7.0.dist-info/RECORD
