Metadata-Version: 2.1
Name: libretrofuzz
Version: 3.7.0
Summary: Fuzzy Retroarch thumbnail downloader
Home-page: https://github.com/i30817/libretrofuzz
License: MIT
Author: i30817
Author-email: i30817@gmail.com
Requires-Python: >=3.8,<4.0
Classifier: License :: OSI Approved :: MIT License
Classifier: Programming Language :: Python :: 3
Classifier: Programming Language :: Python :: 3.10
Classifier: Programming Language :: Python :: 3.8
Classifier: Programming Language :: Python :: 3.9
Requires-Dist: beautifulsoup4 (>=4.12.2,<5.0.0)
Requires-Dist: httpx (>=0.28.1,<0.29.0)
Requires-Dist: pillow (>=10.1.0,<11.0.0); platform_machine not in "aarch64" and platform_machine not in "armv8"
Requires-Dist: prompt_toolkit (>=3.0.36,<4.0.0)
Requires-Dist: questionary (>=2.0.1,<3.0.0)
Requires-Dist: rapidfuzz (>=3.9.7,<4.0.0)
Requires-Dist: regex (>=2023.10.3,<2024.0.0)
Requires-Dist: tqdm (>=4.66.1,<5.0.0)
Requires-Dist: typer[all] (>=0.19.0,<0.20.0)
Project-URL: Bug Tracker, https://github.com/i30817/libretrofuzz/issues
Project-URL: Repository, https://github.com/i30817/libretrofuzz
Project-URL: documentation, https://github.com/i30817/libretrofuzz#readme
Project-URL: homepage, https://github.com/i30817/libretrofuzz
